{
  "Twin Lightning Claws": {
    "num_attacks": 5,
    "skill": 3,
    "strength": 5,
    "armor_pen": 2,
    "damage": 1,
    "count": 8,
    "twin_linked": "True"
  },
  "Power Fist": {
    "num_attacks": 3,
    "skill": 3,
    "strength": 8,
    "armor_pen": 2,
    "damage": 2,
    "count": 8
  },
  "Thunder Hammer": {
    "num_attacks": 3,
    "skill": 4,
    "strength": 8,
    "armor_pen": 2,
    "damage": 2,
    "count": 8,
    "devastating_wounds": "True"
  },
  "Chainfist": {
    "num_attacks": 3,
    "skill": 4,
    "strength": 8,
    "armor_pen": 2,
    "damage": 2,
    "count": 8
  },
  "Chainfist vs Vehicle": {
    "num_attacks": 3,
    "skill": 4,
    "strength": 8,
    "armor_pen": 2,
    "damage": 2,
    "count": 8,
    "critical_wound_value": 3
  }
}
